dtwinpy/Digital_Twin.py
dtwinpy/__init__.py
dtwinpy/broker_manager.py
dtwinpy/components.py
dtwinpy/digital_model.py
dtwinpy/helper.py
dtwinpy/interfaceAPI.py
dtwinpy/interfaceDB.py
dtwinpy/services.py
dtwinpy/synchronizer.py
dtwinpy/tester.py
dtwinpy/updator.py
dtwinpy/validator.py
dtwinpy-0.1.0.dist-info/METADATA
dtwinpy-0.1.0.dist-info/WHEEL
dtwinpy-0.1.0.dist-info/top_level.txt
dtwinpy-0.1.0.dist-info/RECORD
