Metadata-Version: 2.1
Name: dtwinpy
Version: 0.1.0
Summary: Complete DT running
Author: Pedro Bacelar and Alex
License: MIT
